jenkins_cli/__init__.py
jenkins_cli/cli.py
jenkins_cli/client/__init__.py
jenkins_cli/client/jenkins_client.py
jenkins_cli/commands/__init__.py
jenkins_cli/commands/build_cmd.py
jenkins_cli/commands/config_cmd.py
jenkins_cli/commands/console_cmd.py
jenkins_cli/commands/init_cmd.py
jenkins_cli/commands/open_cmd.py
jenkins_cli/commands/status_cmd.py
jenkins_cli/config/__init__.py
jenkins_cli/config/constants.py
jenkins_cli/utils/__init__.py
jenkins_cli/utils/decorators.py
jenkins_cli/utils/display.py
jnks_cli-1.0.0.dist-info/LICENSE
jnks_cli-1.0.0.dist-info/METADATA
jnks_cli-1.0.0.dist-info/WHEEL
jnks_cli-1.0.0.dist-info/entry_points.txt
jnks_cli-1.0.0.dist-info/top_level.txt
jnks_cli-1.0.0.dist-info/RECORD
