Metadata-Version: 2.2
Name: jnks-cli
Version: 1.0.0
Summary: A command-line interface for managing Jenkins jobs
Home-page: https://github.com/iamvinit/jenkins-cli
Author: Jenkins CLI Team
Author-email: iamvinit@users.noreply.github.com
Project-URL: Bug Tracker, https://github.com/iamvinit/jenkins-cli/issues
Project-URL: Documentation, https://github.com/iamvinit/jenkins-cli#readme
Project-URL: Source Code, https://github.com/iamvinit/jenkins-cli
Keywords: jenkins,cli,devops,continuous integration,automation
Classifier: Development Status :: 3 - Alpha
Classifier: Intended Audience :: Developers
Classifier: Topic :: Software Development :: Build Tools
Classifier: Programming Language :: Python :: 3
Classifier: Programming Language :: Python :: 3.7
Classifier: Programming Language :: Python :: 3.8
Classifier: Programming Language :: Python :: 3.9
Classifier: Programming Language :: Python :: 3.10
Classifier: Programming Language :: Python :: 3.11
Classifier: License :: OSI Approved :: MIT License
Classifier: Operating System :: OS Independent
Requires-Python: >=3.7
License-File: LICENSE
Requires-Dist: click>=8.0.0
Requires-Dist: pyyaml>=6.0.0
Requires-Dist: python-jenkins>=1.8.0
Requires-Dist: requests>=2.25.0
Requires-Dist: tabulate>=0.9.0
Requires-Dist: urllib3>=2.0.0
Dynamic: author
Dynamic: author-email
Dynamic: classifier
Dynamic: description
Dynamic: description-content-type
Dynamic: home-page
Dynamic: keywords
Dynamic: project-url
Dynamic: requires-dist
Dynamic: requires-python
Dynamic: summary
